[
  {
    "id": "0",
    "name": "Numanice",
    "date": "Sab, 03 Jun - 14:00",
    "address": "CE Tietê - Parque Harmonia - São Paulo, SP",
    "image": "/images/quadrado.png"
  },
  {
    "id": "1",
    "name": "Serial Funkers",
    "date": "Sab, 03 Jun - 14:00",
    "address": "CE Tietê - Parque Harmonia - São Paulo, SP",
    "image": "/images/quadrado.png"
  },
  {
    "id": "2",
    "name": "Numanice",
    "date": "Sab, 29 Abr - 20:30",
    "address": "Bourbon Street - São Paulo, SP",
    "image": "/images/quadrado.png"
  },
  {
    "id": "3",
    "name": "Blues Beatles",
    "date": "Sex, 12 Mai - 22:00",
    "address": "Bourbon Street - São Paulo, SP",
    "image": "/images/quadrado.png"
  },
  {
    "id": "4",
    "name": "Solarium festival",
    "date": "Dom, 05 Ago - 17:00",
    "address": "Mairiporã - Mairiporã, SP",
    "image": "/images/quadrado.png"
  },
  {
    "id": "5",
    "name": "Festa na Árvore (só vai quem...)",
    "date": "Sex, 12 Set - 3:33",
    "address": "CE Tietê - Parque Harmonia - São Paulo, SP",
    "image": "/images/quadrado.png"
  },
  {
    "id": "6",
    "name": "Numanice",
    "date": "Sab, 03 Jun - 14:00",
    "address": "CE Tietê - Parque Harmonia - São Paulo, SP",
    "image": "/images/quadrado.png"
  },
  {
    "id": "7",
    "name": "Numanice",
    "date": "Sab, 03 Jun - 14:00",
    "address": "CE Tietê - Parque Harmonia - São Paulo, SP",
    "image": "/images/quadrado.png"
  },
  {
    "id": "8",
    "name": "Numanice",
    "date": "Sab, 03 Jun - 14:00",
    "address": "CE Tietê - Parque Harmonia - São Paulo, SP",
    "image": "/images/quadrado.png"
  },
  {
    "id": "9",
    "name": "Numanice",
    "date": "Sab, 03 Jun - 14:00",
    "address": "CE Tietê - Parque Harmonia - São Paulo, SP",
    "image": "/images/quadrado.png"
  }
]
